README.md
setup.py
pyplineCI/__init__.py
pyplineCI/pyplineCI.py
pypline_ci.egg-info/PKG-INFO
pypline_ci.egg-info/SOURCES.txt
pypline_ci.egg-info/dependency_links.txt
pypline_ci.egg-info/requires.txt
pypline_ci.egg-info/top_level.txt