Metadata-Version: 2.1
Name: pypline-ci
Version: 0.1.34
Summary: A docker pipeline library
Home-page: https://github.com/christianTragesser/pypline-ci
Author: Christian Tragesser
Author-email: christian@evoen.net
License: MIT
Platform: UNKNOWN
Classifier: Programming Language :: Python :: 2.7
Classifier: Programming Language :: Python :: 3
Classifier: License :: OSI Approved :: MIT License
Classifier: Operating System :: OS Independent
